free_deepl_translator/__init__.py
free_deepl_translator/deepl_connector.py
free_deepl_translator/deepl_msgpack.py
free_deepl_translator/deepl_property.py
free_deepl_translator/deepl_protobuf.py
free_deepl_translator/deepl_translator.py
free_deepl_translator/json/protobuf.json
free_deepl_translator-1.2.3.dist-info/METADATA
free_deepl_translator-1.2.3.dist-info/WHEEL
free_deepl_translator-1.2.3.dist-info/top_level.txt
free_deepl_translator-1.2.3.dist-info/RECORD
