Metadata-Version: 2.4
Name: free-deepl-translator
Version: 1.2.3
Summary: Unofficial free DeepL translator client (No auth)
Author: Darkcraft
License-Expression: MIT
Requires-Python: >=3.8
Requires-Dist: curl_cffi>=0.6.0
Requires-Dist: msgpack>=1.0.0
Requires-Dist: bbpb>=1.4.2
